{"cameraMode":{"drawMode":0,"name":"Shaded","section":"Shading Mode"},"sceneLighting":true,"audioPlay":false,"sceneViewState":{"m_AlwaysRefresh":false,"showFog":true,"showSkybox":true,"showFlares":true,"showImageEffects":true,"showParticleSystems":true,"showVisualEffectGraphs":true,"m_FxEnabled":true},"in2DMode":false,"pivot":{"x":45.3973388671875,"y":25.875595092773439,"z":343.5646057128906},"rotation":{"x":-0.04951038211584091,"y":-0.007545755244791508,"z":-0.001778094214387238,"w":-0.9991360902786255},"size":540.3616943359375,"orthographic":false}